INSTALL.rst
LICENSE
MANIFEST.in
NEWS.rst
README.rst
pyproject.toml
requirements.txt
setup.py
bin/AlignRecords.py
bin/AssignGenes.py
bin/BuildTrees.py
bin/ConvertDb.py
bin/CreateGermlines.py
bin/DefineClones.py
bin/MakeDb.py
bin/ParseDb.py
changeo/Alignment.py
changeo/Applications.py
changeo/Commandline.py
changeo/Defaults.py
changeo/Distance.py
changeo/Gene.py
changeo/IO.py
changeo/Multiprocessing.py
changeo/Receptor.py
changeo/Version.py
changeo/__init__.py
changeo.egg-info/PKG-INFO
changeo.egg-info/SOURCES.txt
changeo.egg-info/dependency_links.txt
changeo.egg-info/not-zip-safe
changeo.egg-info/requires.txt
changeo.egg-info/top_level.txt
changeo/data/hh_s1f_dist.tsv
changeo/data/hh_s5f_dist.tsv
changeo/data/hs1f_compat_dist.tsv
changeo/data/m1n_compat_dist.tsv
changeo/data/mk_rs1nf_dist.tsv
changeo/data/mk_rs5nf_dist.tsv
tests/test_DefineClones.py
tests/test_Distance.py
tests/test_IO.py
tests/test_ParseDb.py
tests/test_Receptor.py