Metadata-Version: 2.4
Name: changeo
Version: 1.3.4
Summary: A bioinformatics toolkit for processing high-throughput lymphocyte receptor sequencing data.
Home-page: http://changeo.readthedocs.io
Download-URL: https://github.com/immcantation/changeo/tags
Author: Namita Gupta, Jason Anthony Vander Heiden
Author-email: immcantation@googlegroups.com
License: GNU Affero General Public License 3 (AGPL-3)
Keywords: bioinformatics,sequencing,immunology,adaptive immunity,immunoglobulin,AIRR-seq,Rep-Seq,B cell repertoire analysis,adaptive immune receptor repertoires
Classifier: Development Status :: 4 - Beta
Classifier: Environment :: Console
Classifier: Intended Audience :: Science/Research
Classifier: Natural Language :: English
Classifier: Operating System :: OS Independent
Classifier: Programming Language :: Python :: 3.10
Classifier: Topic :: Scientific/Engineering :: Bio-Informatics
License-File: LICENSE
Requires-Dist: numpy>=1.23.2
Requires-Dist: scipy>=1.9.3
Requires-Dist: pandas>=1.5.0
Requires-Dist: biopython>=1.81
Requires-Dist: PyYAML>=6.0
Requires-Dist: setuptools>=65.5.0
Requires-Dist: presto>=0.7.1
Requires-Dist: airr>=1.3.1
Requires-Dist: packaging>=21.3
Requires-Dist: importlib-resources>=6.4.0
Dynamic: author
Dynamic: author-email
Dynamic: classifier
Dynamic: description
Dynamic: download-url
Dynamic: home-page
Dynamic: keywords
Dynamic: license
Dynamic: license-file
Dynamic: requires-dist
Dynamic: summary
